spradius/__init__.py
spradius/alpha_family.py
spradius/generalised_alpha.py
spradius/hht.py
spradius/integrator.py
spradius/newmark.py
spradius-1.0.1.dist-info/LICENSE
spradius-1.0.1.dist-info/METADATA
spradius-1.0.1.dist-info/WHEEL
spradius-1.0.1.dist-info/top_level.txt
spradius-1.0.1.dist-info/RECORD
