Metadata-Version: 2.1
Name: spradius
Version: 1.0.1
Summary: A spectral radius package for time-integration in solid dynamics
Home-page: https://github.com/amcc1996/spradius
Author: António Manuel Couto Carneiro @FEUP
Author-email: amcc@fe.up.pt
License: MIT
Download-URL: https://github.com/amcc1996/spradius/releases/tag/1.0.1
Project-URL: Source, https://github.com/amcc1996/spradius
Project-URL: Tracker, https://github.com/amcc1996/spradius/issues
Keywords: time-integration dynamics spectral-radius python3
Platform: UNKNOWN
Classifier: Development Status :: 4 - Beta
Classifier: Environment :: Console
Classifier: Intended Audience :: Science/Research
Classifier: License :: OSI Approved :: MIT License
Classifier: Natural Language :: English
Classifier: Programming Language :: Python :: 3.6
Classifier: Programming Language :: Python :: 3.7
Classifier: Programming Language :: Python :: 3.8
Classifier: Topic :: Scientific/Engineering
Classifier: Topic :: Scientific/Engineering :: Physics
Requires-Python: >=3.6, <3.9
Requires-Dist: mpmath (>=1.1.0)
Requires-Dist: numpy (>=1.19.4)
Requires-Dist: tqdm (>=4.52.0)
